DFF.v
module DFF (
	input clk,    // Enable
	input clr,	 // Asynchronous clear
	input D,	 // Data input
	output Q,
	output Qbar
);

wire X, Y;
reg Q;
reg Qbar;

always @(posedge clk or negedge clr) 
begin 
	if(~clr) 
	begin
		Q <= 0;
		Qbar <= 1;
	end 
	else 
	begin
		Q <= D;
		Qbar <= ~D;
	end
end

endmodule

DFF_tb.v
`timescale 1s/100ms
`include "DFF.v"

module DFF_tb ();

	reg clk;
	reg clr;
	reg D;
	wire Q;
	wire Qbar;

	DFF myDFF(clk, clr, D, Q, Qbar);
	// DFF myDFF(clk, D, Q, Qbar);

	initial
	begin 
		$monitor("clk = %b, clr = %b, D = %b, Q = %b", clk, clr, D, Q);
		// $monitor("clk = %b, D = %b, Q = %b", clk, D, Q);
		$dumpfile("DFF.vcd");
		$dumpvars(0, DFF_tb);
		clr <= 1;

		clk <= 0;
		D <= 1; #1;
		D <= 0; #1;

		clk <= 1;
		D <= 1; #1;
		D <= 0; #1;

		clk <= 0;
		D <= 1; #1;
		D <= 0; #1;

		clk <= 1;
		D <= 0; #1;
		D <= 1; #1;

		clk <= 0;
		D <= 1; #1;
		D <= 0; #1;

		clk <= 1;
		D <= 1; #1;
		D <= 0; #1;

		clk <= 0;
		D <= 1; #1;
		D <= 0; #1;


		clr <= 0;


		clk <= 1;
		D <= 1; #1;
		D <= 0; #1;

		$finish;
	end

endmodule

DFF.vcd
$date
	Mon Nov 12 22:36:54 2018
$end
$version
	Icarus Verilog
$end
$timescale
	100ms
$end
$scope module DFF_tb $end
$var wire 1 ! Qbar $end
$var wire 1 " Q $end
$var reg 1 # D $end
$var reg 1 $ clk $end
$var reg 1 % clr $end
$scope module myDFF $end
$var wire 1 # D $end
$var wire 1 $ clk $end
$var wire 1 % clr $end
$var reg 1 " Q $end
$var reg 1 ! Qbar $end
$upscope $end
$upscope $end
$enddefinitions $end
#0
$dumpvars
1%
0$
1#
x"
x!
$end
#10
0#
#20
0!
1"
1#
1$
#30
0#
#40
1#
0$
#50
0#
#60
1!
0"
1$
#70
1#
#80
0$
#90
0#
#100
0!
1"
1#
1$
#110
0#
#120
1#
0$
#130
0#
#140
1!
0"
1#
1$
0%
#150
0#
